[
  {
    "username": "Sal",
    "password": "password12345"
  },
  {
    "username": "Lernantino",
    "password": "password12345"
  },
  {
    "username": "Amiko",
    "password": "password12345"
  },
  {
    "username": "Mara_Jade",
    "password": "forceuser456"
  },
  {
    "username": "Neo_Anderson",
    "password": "redpill123"
  },
  {
    "username": "Trinity84",
    "password": "matrixlove"
  },
  {
    "username": "HackerMan",
    "password": "supersecure777"
  },
  {
    "username": "JaneDoe89",
    "password": "janepass89"
  },
  {
    "username": "JohnSmith123",
    "password": "smithsecure456"
  },
  {
    "username": "CoolCat2024",
    "password": "coolpassword2024"
  },
  {
    "username": "RoboCop",
    "password": "lawman9000"
  },
  {
    "username": "SkyWalker",
    "password": "jedi5678"
  },
  {
    "username": "Leia_Organa",
    "password": "princess2024"
  },
  {
    "username": "Spartan117",
    "password": "halo777"
  },
  {
    "username": "SolidSnake",
    "password": "stealthmode999"
  },
  {
    "username": "Ellie_W",
    "password": "lastofus456"
  },
  {
    "username": "Joel_M",
    "password": "clicker123"
  },
  {
    "username": "TombRaider",
    "password": "raider456"
  },
  {
    "username": "DrStrange",
    "password": "sorcery2024"
  },
  {
    "username": "BlackWidow",
    "password": "spy007"
  },
  {
    "username": "TonyStark",
    "password": "ironman2024"
  },
  {
    "username": "CaptainRogers",
    "password": "superSoldier101"
  },
  {
    "username": "Thor_Odinson",
    "password": "thunder2024"
  },
  {
    "username": "Bruce_Wayne",
    "password": "darkknight456"
  },
  {
    "username": "Clark_Kent",
    "password": "kryptonian789"
  },
  {
    "username": "PeterParker",
    "password": "spidey123"
  },
  {
    "username": "WonderWoman",
    "password": "lassooftruth"
  },
  {
    "username": "BarryAllen",
    "password": "fastestman"
  },
  {
    "username": "Arthur_Curry",
    "password": "seaking2024"
  },
  {
    "username": "DianaPrince",
    "password": "amazonwarrior"
  }
]
